xunitparser.py
xunitparser-1.3.4.dist-info/AUTHORS
xunitparser-1.3.4.dist-info/LICENSE
xunitparser-1.3.4.dist-info/METADATA
xunitparser-1.3.4.dist-info/WHEEL
xunitparser-1.3.4.dist-info/top_level.txt
xunitparser-1.3.4.dist-info/RECORD
