Metadata-Version: 2.1
Name: xunitparser
Version: 1.3.4
Summary: Read JUnit/XUnit XML files and map them to Python objects
Home-page: https://gitlab.com/woob/xunitparser/
Author: Laurent Bachelier
Author-email: laurent@bachelier.name
License: UNKNOWN
Platform: UNKNOWN
Classifier: License :: OSI Approved :: MIT License
Classifier: Programming Language :: Python :: 3.4
Classifier: Programming Language :: Python :: 3.5
Classifier: Programming Language :: Python :: 3.6
Classifier: Programming Language :: Python :: 3.7
Classifier: Programming Language :: Python :: 3.8
Classifier: Programming Language :: Python :: 3.9
Classifier: Programming Language :: Python :: 3.10
Classifier: Topic :: Software Development :: Testing
